{
  "id": "4ef4619b-7908-4e6f-9394-befdae7fe152",
  "name": "Get Tooling Describe SObject",
  "url": "{{endpoint}}/services/data/v{{version}}/tooling/sobjects/{sobjectName}/describe",
  "description": "",
  "data": null,
  "dataOptions": null,
  "dataMode": null,
  "headerData": [
    {
      "key": "Authorization",
      "value": "Bearer {{access_token}}"
    }
  ],
  "method": "GET",
  "pathVariableData": [],
  "queryParams": [],
  "auth": null,
  "events": null,
  "folder": "1347ab9b-06a4-4ce3-87d0-b2e76e2ee8eb",
  "currentHelper": null,
  "helperAttributes": null,
  "collectionId": "3514eccb-888f-4bbf-82c4-ba07fdd5173e",
  "headers": "Authorization: Bearer {{access_token}}\n",
  "pathVariables": {}
}