{
  "id": "be613a6d-fc33-4deb-81e1-9afaa3541332",
  "name": "List of Groups",
  "url": "{{_endpoint}}/services/data/v{{version}}/chatter/groups",
  "description": "A list of all the groups in the organization. Get information about groups or create a group.\n\nhttps://developer.salesforce.com/docs/atlas.en-us.chatterapi.meta/chatterapi/connect_resources_groups_ListOfGroups.htm",
  "data": null,
  "dataOptions": null,
  "dataMode": null,
  "headerData": [],
  "method": "GET",
  "pathVariableData": [],
  "queryParams": [],
  "auth": null,
  "events": [
    {
      "listen": "prerequest",
      "script": {
        "id": "2950ba8d-f28b-4ac8-8c2b-f4702695db7a",
        "exec": [
          ""
        ],
        "type": "text/javascript"
      }
    },
    {
      "listen": "test",
      "script": {
        "id": "f976136d-f6ef-4acb-b959-e40d3c1bf9f8",
        "exec": [
          ""
        ],
        "type": "text/javascript"
      }
    }
  ],
  "folder": "9d7a1985-ec3a-4198-a7b5-b9b309479c49",
  "protocolProfileBehavior": {
    "disabledSystemHeaders": {}
  },
  "preRequestScript": null,
  "tests": null,
  "currentHelper": null,
  "helperAttributes": null,
  "collectionId": "314d5e58-9fdf-470c-aa02-621a1feb568e",
  "headers": "",
  "pathVariables": {}
}