{
  "id": "0c614f81-065c-49b9-b86f-09a0fb38c576",
  "name": "Get Appointment Slots",
  "url": "{{endpoint}}/services/data/v{{version}}/scheduling/getAppointmentSlots",
  "description": "Returns a list of available appointment time slots for a resource based on given work type group and territories.\n\nhttps://developer.salesforce.com/docs/atlas.en-us.api_rest.meta/api_rest/requests_ls_getappointmentslots.htm",
  "data": [],
  "dataOptions": null,
  "dataMode": "raw",
  "headerData": [
    {
      "key": "Authorization",
      "value": "Bearer {{access_token}}"
    },
    {
      "key": "Content-Type",
      "value": "application/json"
    }
  ],
  "method": "POST",
  "pathVariableData": [],
  "queryParams": [],
  "auth": null,
  "events": null,
  "folder": "782b69d1-36f1-4b89-a2c4-a09e74d4acfa",
  "currentHelper": null,
  "helperAttributes": null,
  "collectionId": "ad0a8738-1c8a-4ec4-907c-7b6af7470f21",
  "rawModeData": "{\n\t\"startTime\": \"string\",\n\t\"endTime\": \"string\",\n\t\"workTypeGroupId\": \"string\",\n\t\"workType\": \"Work Type\",\n\t\"accountId\": \"string\",\n\t\"territoryIds\": \"string[]\",\n\t\"requiredResourceIds\": \"string[]\",\n\t\"schedulingPolicyId\": \"string\",\n\t\"allowConcurrentScheduling\": \"boolean\",\n}",
  "headers": "Authorization: Bearer {{access_token}}\nContent-Type: application/json\n",
  "pathVariables": {}
}